pip_services4_persistence/__init__.py
pip_services4_persistence/persistence/FilePersistence.py
pip_services4_persistence/persistence/IdentifiableFilePersistence.py
pip_services4_persistence/persistence/IdentifiableMemoryPersistence.py
pip_services4_persistence/persistence/JsonFilePersister.py
pip_services4_persistence/persistence/MemoryPersistence.py
pip_services4_persistence/persistence/__init__.py
pip_services4_persistence/read/IFilteredPageReader.py
pip_services4_persistence/read/IFilteredReader.py
pip_services4_persistence/read/IGetter.py
pip_services4_persistence/read/ILoader.py
pip_services4_persistence/read/IQuerablePageReader.py
pip_services4_persistence/read/IQuerableReader.py
pip_services4_persistence/read/__init__.py
pip_services4_persistence/write/IPartialUpdater.py
pip_services4_persistence/write/ISaver.py
pip_services4_persistence/write/ISetter.py
pip_services4_persistence/write/IWriter.py
pip_services4_persistence/write/__init__.py
pip_services4_persistence-0.0.2.dist-info/LICENSE
pip_services4_persistence-0.0.2.dist-info/METADATA
pip_services4_persistence-0.0.2.dist-info/WHEEL
pip_services4_persistence-0.0.2.dist-info/top_level.txt
pip_services4_persistence-0.0.2.dist-info/zip-safe
pip_services4_persistence-0.0.2.dist-info/RECORD
